flaskion_cli/__init__.py
flaskion_cli/cli.py
flaskion_cli/cli_templates/api_route_template.py.jinja
flaskion_cli/cli_templates/auth_controller_template.py.jinja
flaskion_cli/cli_templates/controller_template.py.jinja
flaskion_cli/cli_templates/model_template.py.jinja
flaskion_cli/cli_templates/schema_template.py.jinja
flaskion_cli/cli_templates/user_model_template.py.jinja
flaskion_cli/cli_templates/user_schema_template.py.jinja
flaskion_cli/cli_templates/web_route_template.py.jinja
flaskion_cli/cli_templates/html/auth/dashboard.html.jinja
flaskion_cli/cli_templates/html/auth/login.html.jinja
flaskion_cli/cli_templates/html/auth/register.html.jinja
flaskion_cli/flaskion_template/.DS_Store
flaskion_cli/flaskion_template/.env.example
flaskion_cli/flaskion_template/.gitattributes
flaskion_cli/flaskion_template/.gitignore
flaskion_cli/flaskion_template/requirements.txt
flaskion_cli/flaskion_template/run.py
flaskion_cli/flaskion_template/app/.DS_Store
flaskion_cli/flaskion_template/app/__init__.py
flaskion_cli/flaskion_template/app/config.py
flaskion_cli/flaskion_template/app/controllers/__init__.py
flaskion_cli/flaskion_template/app/controllers/api_controller.py
flaskion_cli/flaskion_template/app/controllers/hello_controller.py
flaskion_cli/flaskion_template/app/models/__init__.py
flaskion_cli/flaskion_template/app/models/example.py
flaskion_cli/flaskion_template/app/models/mixin.py
flaskion_cli/flaskion_template/app/routes/__init__.py
flaskion_cli/flaskion_template/app/routes/api_routes.py
flaskion_cli/flaskion_template/app/routes/web_routes.py
flaskion_cli/flaskion_template/app/schemas/example_schema.py
flaskion_cli/flaskion_template/app/static/.DS_Store
flaskion_cli/flaskion_template/app/static/css/style.css
flaskion_cli/flaskion_template/app/static/images/logo.png
flaskion_cli/flaskion_template/app/templates/base.html
flaskion_cli/flaskion_template/app/templates/hello.html
flaskion_cli-1.0.10.1.dist-info/METADATA
flaskion_cli-1.0.10.1.dist-info/WHEEL
flaskion_cli-1.0.10.1.dist-info/entry_points.txt
flaskion_cli-1.0.10.1.dist-info/top_level.txt
flaskion_cli-1.0.10.1.dist-info/RECORD
