Metadata-Version: 2.1
Name: flaskion-cli
Version: 1.0.10.1
Summary: A CLI tool for Flaskion — a lightweight MVC micro-framework built on Flask
Home-page: https://github.com/GrahamMorbyDev/flaskion
Author: Graham Patrick
Author-email: graham@skyaisoftware.com
Classifier: Programming Language :: Python :: 3
Classifier: License :: OSI Approved :: MIT License
Classifier: Operating System :: OS Independent
Requires-Python: >=3.6
Requires-Dist: click>=8.0
Requires-Dist: jinja2>=3.0
